{
    "debug_level": 0,
    "input_file": "./neural/sample_grids/inv_cylinder-50.cas",
    "output_file": "output",
    "parts": [
        {
            "name": "inflow",
            "max_size": 2.0,
            "PRISM_SWITCH": false,
            "first_height": 0.1,
            "max_layers": 5,
            "full_layers": 5,
            "multi_direction": false
        },
        {
            "name": "bc-3",
            "max_size": 2.0,
            "PRISM_SWITCH": true,
            "first_height": 0.1,
            "max_layers": 5,
            "full_layers": 5,
            "multi_direction": false
        }
    ]
}